{
  "openapiConfig": {
    "filePath": "./openapi3.yaml",
    "basePath": "/docs",
    "rawPath": "/api",
    "uiPath": "/api"
  },
  "logger": {
    "level": "info"
  },
  "server": {
    "port": "8080",
    "request": {
      "payload": {
        "limit": "1mb"
      }
    },
    "response": {
      "compression": {
        "enabled": true,
        "options": null
      }
    }
  },
  "db": {
    "type": "postgres",
    "host": "localhost",
    "port": 5432,
    "username": "avi",
    "password": "avi",
    "enableSslAuth": false,
    "sslPaths": {
      "ca": "",
      "key": "",
      "cert": ""
    },
    "database": "avi",
    "schema": "id_2_osm"
  }
}
